{
  "pers_r6": 2, 
  "pers_r7": 0, 
  "pers_r4": 2, 
  "man_hardware": "cluster", 
  "pers_r2": 2, 
  "pers_r3": 0, 
  "pers_r1": 2, 
  "man_r4": 0, 
  "man_r3": 3, 
  "man_r2": 2, 
  "pers_r8": 3, 
  "pers_r5": 3, 
  "man_os": "fedora", 
  "remote_addr": "84.115.x.x", 
  "sw_general": [
    "cpp", 
    "mathematica", 
    "python"
  ], 
  "pers_maint_time": 5.0, 
  "bg_position": "ra", 
  "pers_time": "always", 
  "pers_hardware": "cluster", 
  "bg_employer": "edu_pub", 
  "man_time": "always", 
  "sw_neusys": [
    "pcsim"
  ], 
  "pers_os": "fedora", 
  "timestamp": 1305705603.9719851, 
  "software_resource": [
    "epel", 
    "pythonbundles", 
    "sourceforge"
  ], 
  "man_r1": 3, 
  "bg_datamod": [
    "simulation"
  ], 
  "bg_developer": "yes", 
  "sw_other_name": "", 
  "virt_time": "notime", 
  "success": true, 
  "software_resource_other": "", 
  "virt_host_os": "none", 
  "virt_guest_os": "none", 
  "virt_other": "", 
  "user_agent": "Mozilla/5.0 (Windows NT 6.1; WOW64; rv:2.0.1) Gecko/20100101 Firefox/4.0.1", 
  "sw_dc": [
    "torque", 
    "mpi", 
    "ipython"
  ], 
  "bg_country": "Austria", 
  "bg_datamod_other": ""
}