{
  "pers_r6": 2, 
  "pers_r7": 1, 
  "pers_r4": 1, 
  "man_hardware": "none", 
  "pers_r2": 3, 
  "pers_r3": 2, 
  "pers_r1": 1, 
  "man_r4": 3, 
  "man_r3": 0, 
  "man_r2": 0, 
  "pers_r8": 3, 
  "pers_r5": 3, 
  "virt_r3": 1, 
  "man_os": "none", 
  "remote_addr": "164.67.x.x", 
  "sw_img": [
    "trackvis", 
    "fsl", 
    "freesurfer", 
    "mricron", 
    "spm"
  ], 
  "sw_general": [
    "matlab", 
    "shell"
  ], 
  "virt_prod": [
    "vmware"
  ], 
  "bg_position": "professor", 
  "pers_time": "little", 
  "virt_r1": 3, 
  "bg_datamod": [
    "behav", 
    "mri"
  ], 
  "virt_r2": 2, 
  "virt_r4": 2, 
  "bg_employer": "edu_pub", 
  "man_time": "notime", 
  "pers_maint_time": 10.0, 
  "pers_os": "windows", 
  "timestamp": 1305759481.3691311, 
  "software_resource": [
    "vendor", 
    "matlabcentral", 
    "sourceforge", 
    "otherres"
  ], 
  "man_r1": 2, 
  "pers_hardware": "workstation", 
  "bg_developer": "yes", 
  "sw_other_name": "", 
  "virt_time": "little", 
  "success": true, 
  "software_resource_other": "various researchers making their tools available", 
  "virt_host_os": "windows", 
  "virt_guest_os": "centos", 
  "virt_other": "", 
  "user_agent": "Mozilla/5.0 (Windows NT 5.1; rv:2.0.1) Gecko/20100101 Firefox/4.0.1", 
  "bg_country": "United States", 
  "bg_datamod_other": ""
}