{
  "pers_r6": 2, 
  "pers_r7": 3, 
  "pers_r4": 1, 
  "man_hardware": "none", 
  "pers_r2": 3, 
  "pers_r3": 2, 
  "pers_r1": 2, 
  "pers_r8": 3, 
  "pers_r5": 3, 
  "virt_r3": 2, 
  "man_os": "none", 
  "remote_addr": "129.85.x.x", 
  "sw_img": [
    "imagej"
  ], 
  "sw_general": [
    "cpp", 
    "matlab", 
    "shell"
  ], 
  "virt_prod": [
    "vmware"
  ], 
  "bg_position": "professor", 
  "pers_time": "most", 
  "virt_r1": 3, 
  "bg_datamod": [
    "simulation"
  ], 
  "virt_r2": 0, 
  "virt_r4": 2, 
  "bg_employer": "edu_priv", 
  "man_time": "notime", 
  "pers_maint_time": 2.0, 
  "pers_os": "rhel", 
  "timestamp": 1306262961.7177589, 
  "software_resource": [
    "vendor", 
    "os", 
    "sourceforge"
  ], 
  "pers_hardware": "laptop", 
  "bg_developer": "yes", 
  "sw_other_name": "", 
  "virt_time": "little", 
  "success": true, 
  "software_resource_other": "", 
  "virt_host_os": "rhel", 
  "virt_guest_os": "windows", 
  "virt_other": "", 
  "user_agent": "Mozilla/5.0 (X11; U; Linux x86_64; en-US; rv:1.9.2.17) Gecko/20110421 Red Hat/3.6-1.el5_6 Firefox/3.6.17", 
  "bg_country": "United States", 
  "bg_datamod_other": ""
}